cco_cmath.cpython-38.so
cco_cmath-0.0.1.dist-info/LICENSE.txt
cco_cmath-0.0.1.dist-info/METADATA
cco_cmath-0.0.1.dist-info/WHEEL
cco_cmath-0.0.1.dist-info/top_level.txt
cco_cmath-0.0.1.dist-info/RECORD
