Metadata-Version: 2.1
Name: cco-cmath
Version: 0.0.1
Summary: A recall for the cmath header
Home-page: https://github.com/phoxett/cco_cmath
Author: Phoxett
Author-email: phoxett@gmail.com
Maintainer: Phoxett
Maintainer-email: phoxett@gmail.com
License: MIT
Platform: UNKNOWN
Requires-Python: >=3.4.0
